drifting/__init__.py
drifting/drifting_client.py
drifting/drifting_logging.py
drifting/utils.py
drifting/version.py
drifting/detectors/__init__.py
drifting/detectors/alibi_detector.py
drifting/detectors/detector_core.py
drifting/detectors/dummy.py
drifting/detectors/label.py
drifting/detectors/tabular.py
drifting/drift_detection_server/__init__.py
drifting/drift_detection_server/server.py
drifting/storage/__init__.py
drifting/storage/persistor.py
drifting/storage/storage_gcs.py
drifting/storage/storage_interface.py
drifting/storage/storage_s3.py
drifting-0.2.1.dist-info/LICENSE
drifting-0.2.1.dist-info/METADATA
drifting-0.2.1.dist-info/WHEEL
drifting-0.2.1.dist-info/entry_points.txt
drifting-0.2.1.dist-info/top_level.txt
drifting-0.2.1.dist-info/RECORD
