Metadata-Version: 2.1
Name: drifting
Version: 0.2.1
Summary: Drift detection server and client in Python
Home-page: https://github.com/sign-ai/drifting/
Author: SignAI
Author-email: smolendawid@gmail.com
License: Apache 2.0
Platform: UNKNOWN
License-File: LICENSE
Requires-Dist: mlserver
Requires-Dist: alibi-detect
Requires-Dist: requests
